{
  "annotations": [
    {
      "class": "char",
      "boundingBox": {
        "x": 137.6609336609337,
        "y": 210.44420021274902,
        "width": 91.77395577395578,
        "height": 207.2825552825553
      }
    },
    {
      "class": "char",
      "boundingBox": {
        "x": 287.980343980344,
        "y": 216.77641277641277,
        "width": 94.9385749385749,
        "height": 204.1179361179361
      }
    },
    {
      "class": "char",
      "boundingBox": {
        "x": 552.2260442260442,
        "y": 398.74201474201476,
        "width": 79.11547911547916,
        "height": 31.646191646191653
      }
    },
    {
      "class": "char",
      "boundingBox": {
        "x": 792.7371007371007,
        "y": 256.33415233415235,
        "width": 50.63390663390669,
        "height": 174.05405405405406
      }
    },
    {
      "class": "char",
      "boundingBox": {
        "x": 875.017199017199,
        "y": 242.0933660933661,
        "width": 196.20638820638817,
        "height": 181.96560196560196
      }
    },
    {
      "class": "char",
      "boundingBox": {
        "x": 1333.8869778869787,
        "y": 265.8250355935844,
        "width": 104.4324324324325,
        "height": 196.20638820638817
      }
    },
    {
      "class": "char",
      "boundingBox": {
        "x": 1577.5626535626573,
        "y": 227.85257985258016,
        "width": 180.3832923832922,
        "height": 167.72481572481573
      }
    }
  ]
}