{
  "annotations": [
    {
      "class": "char",
      "boundingBox": {
        "x": 8.820512820512821,
        "y": 61.19230769230769,
        "width": 32.52564102564102,
        "height": 63.39743589743591
      }
    },
    {
      "class": "char",
      "boundingBox": {
        "x": 87.65384615384615,
        "y": 69.46153846153848,
        "width": 29.769230769230774,
        "height": 31.42307692307692
      }
    },
    {
      "class": "char",
      "boundingBox": {
        "x": 164.83333333333331,
        "y": 40.24358974358975,
        "width": 25.358974358974365,
        "height": 57.333333333333336
      }
    },
    {
      "class": "char",
      "boundingBox": {
        "x": 244.21794871794873,
        "y": 68.35897435897436,
        "width": 38.03846153846155,
        "height": 11.025641025641022
      }
    },
    {
      "class": "char",
      "boundingBox": {
        "x": 328.5641025641026,
        "y": 28.115384615384617,
        "width": 33.076923076923094,
        "height": 55.12820512820514
      }
    },
    {
      "class": "char",
      "boundingBox": {
        "x": 407.3974358974359,
        "y": 41.34615384615385,
        "width": 41.34615384615387,
        "height": 38.03846153846154
      }
    },
    {
      "class": "char",
      "boundingBox": {
        "x": 477.9615384615385,
        "y": 22.051282051282058,
        "width": 30.87179487179492,
        "height": 64.5
      }
    }
  ]
}