{
  "annotations": [
    {
      "class": "char",
      "boundingBox": {
        "x": 103.16112084063047,
        "y": 348.7828371278459,
        "width": 34.38704028021016,
        "height": 152.28546409807353
      }
    },
    {
      "class": "char",
      "boundingBox": {
        "x": 160.47285464098073,
        "y": 356.97022767075305,
        "width": 47.48686514886165,
        "height": 111.34851138353764
      }
    },
    {
      "class": "char",
      "boundingBox": {
        "x": 271.8213660245184,
        "y": 392.99474605954464,
        "width": 49.12434325744306,
        "height": 63.861646234676016
      }
    },
    {
      "class": "char",
      "boundingBox": {
        "x": 401.1821366024518,
        "y": 358.6077057793345,
        "width": 68.77408056042032,
        "height": 85.1488616462347
      }
    },
    {
      "class": "char",
      "boundingBox": {
        "x": 489.6059544658494,
        "y": 345.507880910683,
        "width": 40.93695271453595,
        "height": 130.9982486865149
      }
    },
    {
      "class": "char",
      "boundingBox": {
        "x": 566.5674255691769,
        "y": 417.5569176882662,
        "width": 47.486865148861625,
        "height": 11.462346760070034
      }
    },
    {
      "class": "char",
      "boundingBox": {
        "x": 659.9036777583187,
        "y": 338.9579684763573,
        "width": 47.486865148861625,
        "height": 150.6479859894921
      }
    },
    {
      "class": "char",
      "boundingBox": {
        "x": 756.5148861646235,
        "y": 365.1576182136602,
        "width": 76.96147110332743,
        "height": 76.96147110332754
      }
    },
    {
      "class": "char",
      "boundingBox": {
        "x": 890.7880910683012,
        "y": 396.2697022767075,
        "width": 47.486865148861625,
        "height": 13.099824868651524
      }
    },
    {
      "class": "char",
      "boundingBox": {
        "x": 977.5744308231173,
        "y": 322.5831873905429,
        "width": 47.48686514886174,
        "height": 111.34851138353764
      }
    },
    {
      "class": "char",
      "boundingBox": {
        "x": 1054.535901926445,
        "y": 334.045534150613,
        "width": 39.2994746059544,
        "height": 130.99824868651484
      }
    }
  ]
}