{
  "annotations": [
    {
      "class": "char",
      "boundingBox": {
        "x": 120.31331592689295,
        "y": 155.40469973890342,
        "width": 68.5117493472585,
        "height": 20.05221932114881
      }
    },
    {
      "class": "char",
      "boundingBox": {
        "x": 227.2584856396867,
        "y": 83.55091383812011,
        "width": 21.723237597911208,
        "height": 113.62924281984336
      }
    },
    {
      "class": "char",
      "boundingBox": {
        "x": 265.69190600522194,
        "y": 90.23498694516972,
        "width": 83.55091383812015,
        "height": 103.60313315926892
      }
    },
    {
      "class": "char",
      "boundingBox": {
        "x": 449.5039164490862,
        "y": 118.64229765013056,
        "width": 70.18276762402093,
        "height": 85.22193211488252
      }
    },
    {
      "class": "char",
      "boundingBox": {
        "x": 574.8302872062663,
        "y": 83.55091383812011,
        "width": 41.77545691906005,
        "height": 132.01044386422979
      }
    },
    {
      "class": "char",
      "boundingBox": {
        "x": 653.3681462140993,
        "y": 81.87989556135771,
        "width": 48.45953002610963,
        "height": 137.023498694517
      }
    },
    {
      "class": "char",
      "boundingBox": {
        "x": 721.8798955613578,
        "y": 173.78590078328983,
        "width": 71.85378590078324,
        "height": 16.71018276762402
      }
    },
    {
      "class": "char",
      "boundingBox": {
        "x": 822.1409921671019,
        "y": 80.2088772845953,
        "width": 73.52480417754566,
        "height": 132.01044386422979
      }
    },
    {
      "class": "char",
      "boundingBox": {
        "x": 925.7441253263709,
        "y": 60.15665796344648,
        "width": 46.78851174934721,
        "height": 182.14099216710184
      }
    }
  ]
}